LICENSE
MANIFEST.in
README.md
setup.py
pension/__init__.py
pension/cli.py
pension/notify.py
pension.egg-info/PKG-INFO
pension.egg-info/SOURCES.txt
pension.egg-info/dependency_links.txt
pension.egg-info/entry_points.txt
pension.egg-info/requires.txt
pension.egg-info/top_level.txt