Metadata-Version: 1.0
Name: pension
Version: 0.0.3
Summary: Alert when ec2 instances are scheduled for retirement
Home-page: https://github.com/erik/pension
Author: Erik Price
Author-email: UNKNOWN
License: MIT
Platform: UNKNOWN
